bugyi/lib/__init__.py
bugyi/lib/core.py
bugyi/lib/dates.py
bugyi/lib/errors.py
bugyi/lib/io.py
bugyi/lib/meta.py
bugyi/lib/py.typed
bugyi/lib/secrets.py
bugyi/lib/shell.py
bugyi/lib/types.py
bugyi/lib/xdg.py
bugyi.lib-0.11.0.dist-info/METADATA
bugyi.lib-0.11.0.dist-info/WHEEL
bugyi.lib-0.11.0.dist-info/top_level.txt
bugyi.lib-0.11.0.dist-info/RECORD
