Metadata-Version: 2.1
Name: bugyi.lib
Version: 0.11.0
Summary: Overly general Python library used when no other library is a good fit.
Home-page: https://github.com/bbugyi200/python-lib
Author: Bryan M Bugyi
Author-email: bryanbugyi34@gmail.com
License: MIT license
Platform: UNKNOWN
Classifier: Development Status :: 3 - Alpha
Classifier: Intended Audience :: Developers
Classifier: License :: OSI Approved :: MIT License
Classifier: Natural Language :: English
Classifier: Programming Language :: Python :: 3
Classifier: Programming Language :: Python :: 3.7
Classifier: Programming Language :: Python :: 3.8
Classifier: Programming Language :: Python :: 3.9
Classifier: Programming Language :: Python :: 3.8
Classifier: Programming Language :: Python :: 3.9
Classifier: Programming Language :: Python :: 3.10
Requires-Python: >=3.8
Requires-Dist: python-dateutil
Requires-Dist: python-result (~=0.2)
Requires-Dist: typing-extensions ; python_version < "3.8"
